setup.py
Gaussian_and_Binomial_distributions/Binomialdistribution.py
Gaussian_and_Binomial_distributions/Gaussiandistribution.py
Gaussian_and_Binomial_distributions/Generaldistribution.py
Gaussian_and_Binomial_distributions/__init__.py
Gaussian_and_Binomial_distributions.egg-info/PKG-INFO
Gaussian_and_Binomial_distributions.egg-info/SOURCES.txt
Gaussian_and_Binomial_distributions.egg-info/dependency_links.txt
Gaussian_and_Binomial_distributions.egg-info/not-zip-safe
Gaussian_and_Binomial_distributions.egg-info/top_level.txt