Metadata-Version: 1.0
Name: Gaussian-and-Binomial-distributions
Version: 0.1
Summary: Gaussian and Binomial distributions
Home-page: UNKNOWN
Author: Vasilis Kontonis
Author-email: kontonisbill@gmail.com
License: UNKNOWN
Platform: UNKNOWN
